non_venomous/__init__.py
non_venomous/architecture.s.HTML
non_venomous/license.S.HTML
non_venomous/module.MD
non_venomous/module.s.HTML
non_venomous/__agenda/maybes.s.HTML
non_venomous/__agenda/priorities.s.HTML
non_venomous/__agenda/processes/errout/script.py
non_venomous/__agenda/processes/errout/start.py
non_venomous/__agenda/processes/errout_v1/script.py
non_venomous/__agenda/processes/errout_v1/start.py
non_venomous/__agenda/processes/errout_v2/script.py
non_venomous/__agenda/processes/errout_v2/start.py
non_venomous/_book/advanced tutorial.s.HTML
non_venomous/_book/book.s.HTML
non_venomous/_book/example output.s.HTML
non_venomous/_book/relevant.s.HTML
non_venomous/_clique/__init__.py
non_venomous/_clique/group/__init__.py
non_venomous/_status/establish.py
non_venomous/_status/status.proc.py
non_venomous/_status/status.s.HTML
non_venomous/_status/status_py.py
non_venomous/_status/DB/records.json
non_venomous/_status/monitors/-1_start/status_1.py
non_venomous/_status/monitors/-1_start/chassis/modules/monitor_1.py
non_venomous/_status/monitors/0_start/status_1.py
non_venomous/_status/monitors/0_start/chassis/modules/monitor_1.py
non_venomous/_status/monitors/1/status_1.py
non_venomous/_status/monitors/1/stasis/path_1_health.py
non_venomous/_status/monitors/1/stasis/path_2_health.py
non_venomous/_status/monitors/2/status_1.py
non_venomous/_status/monitors/2/stasis/1_health.py
non_venomous/_status/monitors/2/stasis/2_health.py
non_venomous/_status/monitors/2/stasis/modules/MODULE_1.py
non_venomous/_status/monitors/3_empty_glob/status_1.py
non_venomous/_status/monitors/4_bad_import/status_1.py
non_venomous/_status/monitors/4_bad_import/stasis/1_health.py
non_venomous/_status/monitors/5__file__/status_1.py
non_venomous/_status/monitors/5__file__/stasis/1_health.py
non_venomous/_status/monitors/5__file__/stasis/MODULES/MODULE_1.py
non_venomous/_status/monitors/6_various/status_1.py
non_venomous/_status/monitors/6_various/stasis/1_health.py
non_venomous-1.2.2.dist-info/METADATA
non_venomous-1.2.2.dist-info/WHEEL
non_venomous-1.2.2.dist-info/entry_points.txt
non_venomous-1.2.2.dist-info/top_level.txt
non_venomous-1.2.2.dist-info/RECORD
