Metadata-Version: 2.1
Name: non_venomous
Version: 1.2.2
Summary: health checks module
License: GPL 3.0
Project-URL: GitLab, https://gitlab.com/status600/climates/non_venomous
Keywords: homeostasis,reliability,consistency,integrity,guarantees,vows,oaths,assurances,insurances,ensurances,speed,calmness,education,augmentation,enhancement,improvements
Requires-Python: >=3.8
Requires-Dist: body-scan
Requires-Dist: botanist
Requires-Dist: shares
Requires-Dist: click
Requires-Dist: coverage
Requires-Dist: flask
Requires-Dist: pdoc3
Requires-Dist: pexpect
Requires-Dist: redis
Requires-Dist: requests
Requires-Dist: textual
Requires-Dist: tinydb
